{
  "project_info": {
    "project_number": "690027021065",
    "firebase_url": "https://board-app-ec924.firebaseio.com",
    "project_id": "board-app-ec924",
    "storage_bucket": "board-app-ec924.appspot.com"
  },
  "client": [
    {
      "client_info": {
        "mobilesdk_app_id": "1:690027021065:android:793d117cfc8672d29ec9d8",
        "android_client_info": {
          "package_name": "com.app.firebase_board_app"
        }
      },
      "oauth_client": [
        {
          "client_id": "690027021065-g9r774lecdbhpc7ssj0guvj4dgk75fa4.apps.googleusercontent.com",
          "client_type": 3
        }
      ],
      "api_key": [
        {
          "current_key": "AIzaSyCTkEABFydSX1IjJLIfZcCIbRGvQyneHQs"
        }
      ],
      "services": {
        "appinvite_service": {
          "other_platform_oauth_client": [
            {
              "client_id": "690027021065-g9r774lecdbhpc7ssj0guvj4dgk75fa4.apps.googleusercontent.com",
              "client_type": 3
            }
          ]
        }
      }
    }
  ],
  "configuration_version": "1"
}